firetail_lambda/__init__.py
firetail_lambda/version.py
Firetail_Lambda-0.1.8.dist-info/LICENSE
Firetail_Lambda-0.1.8.dist-info/METADATA
Firetail_Lambda-0.1.8.dist-info/WHEEL
Firetail_Lambda-0.1.8.dist-info/top_level.txt
Firetail_Lambda-0.1.8.dist-info/RECORD
