Metadata-Version: 2.1
Name: Firetail-Lambda
Version: 0.1.8
Summary: Firetail Lambda Package
Home-page: https://github.com/firetail-io/firetail-py-lambda
Author: Riley Priddle
Author-email: riley@firetail.io
License: LGPLv3
Project-URL: Documentation, https://github.com/firetail-io/firetail-py-lambda
Project-URL: Bug Reports, https://github.com/firetail-io/firetail-py-lambda/issues
Project-URL: Source Code, https://github.com/firetail-io/firetail-py-lambda
Keywords: pypi,package
Classifier: Development Status :: 5 - Production/Stable
Classifier: Environment :: Web Environment
Classifier: Intended Audience :: Developers
Classifier: Programming Language :: Python :: 3
Classifier: Programming Language :: Python :: 3.7
Classifier: Programming Language :: Python :: 3.8
Classifier: Programming Language :: Python :: 3.9
Classifier: Programming Language :: Python :: 3 :: Only
Classifier: Operating System :: OS Independent
Classifier: Topic :: Internet :: WWW/HTTP :: Dynamic Content
Classifier: Topic :: Software Development :: Libraries :: Python Modules
Classifier: Programming Language :: Python :: 3.10
Requires-Python: >=3.7
License-File: LICENSE
Provides-Extra: dev
Requires-Dist: check-manifest ; extra == 'dev'
